CONTRIBUTORS
MANIFEST.in
README.md
setup.py
django_moip/__init__.py
django_moip.egg-info/PKG-INFO
django_moip.egg-info/SOURCES.txt
django_moip.egg-info/dependency_links.txt
django_moip.egg-info/requires.txt
django_moip.egg-info/top_level.txt
django_moip/html/__init__.py
django_moip/html/conf.py
django_moip/html/forms.py
django_moip/html/helpers.py
django_moip/html/models.py
django_moip/html/widgets.py
django_moip/html/nit/__init__.py
django_moip/html/nit/admin.py
django_moip/html/nit/forms.py
django_moip/html/nit/models.py
django_moip/html/nit/signals.py
django_moip/html/nit/urls.py
django_moip/html/nit/views.py
django_moip/html/nit/tests/__init__.py
django_moip/html/nit/tests/test_ipn.py
django_moip/html/nit/tests/test_urls.py
django_moip/html/redirector/__init__.py
django_moip/html/redirector/admin.py
django_moip/html/redirector/forms.py
django_moip/html/redirector/models.py
django_moip/html/redirector/signals.py
django_moip/html/redirector/urls.py
django_moip/html/redirector/views.py
django_moip/html/redirector/tests/__init__.py
django_moip/html/redirector/tests/test_pdt.py
django_moip/html/redirector/tests/test_urls.py