Metadata-Version: 1.1
Name: django-moip
Version: 0.1.1
Summary: A pluggable Django application for integrating MoIP HTML (for now)
Home-page: http://github.com/alanjds/django-moip
Author: Alan Justino da Silva
Author-email: alan.justino@yahoo.com.br
License: UNKNOWN
Download-URL: https://github.com/alanjds/django-moip/tarball/0.1.1
Platform: UNKNOWN
Classifier: Framework :: Django
Classifier: Intended Audience :: Developers
Classifier: Intended Audience :: System Administrators
Classifier: Operating System :: OS Independent
Classifier: Topic :: Software Development
